LICENSE
MANIFEST.in
README.rst
setup.cfg
setup.py
when.py
tests/test_easter_eggs.py
tests/test_when.py
whenpy.egg-info/PKG-INFO
whenpy.egg-info/SOURCES.txt
whenpy.egg-info/dependency_links.txt
whenpy.egg-info/requires.txt
whenpy.egg-info/top_level.txt