Metadata-Version: 1.0
Name: whenpy
Version: 0.3.0
Summary: Friendly Dates and Times
Home-page: https://github.com/dirn/When.py
Author: Andy Dirnberger
Author-email: dirn@dirnonline.com
License: Copyright (c) 2012, Andy Dirnberger
